mfyreport/__init__.py
mfyreport/core/__init__.py
mfyreport/core/dataDriver.py
mfyreport/core/parameterized.py
mfyreport/core/reRun.py
mfyreport/core/resultPush.py
mfyreport/core/sendEmail.py
mfyreport/core/testResult.py
mfyreport/core/testRunner.py
mfyreport/templates/__init__.py
mfyreport/templates/dingtalk.md
mfyreport/templates/templates.html
mfyreport/templates/templates03.html
mfyreport/templates/templates2.html
mfyreport/templates/templates3.html
mfyreport-2.0.2.dist-info/LICENSE
mfyreport-2.0.2.dist-info/METADATA
mfyreport-2.0.2.dist-info/WHEEL
mfyreport-2.0.2.dist-info/top_level.txt
mfyreport-2.0.2.dist-info/RECORD
